{
	"MatplotlibCanvas": {
		"canvas_args": {
			"manager": "pack",
			"side": "left"
		}
	},
	"PMI": {
		"frame_args": {
			"manager": "grid",
			"row": 0,
			"column": 1,
			"sticky": "WE"
		}

	},
	"TimeSeries": {
		"frame_args": {
			"manager": "grid",
			"row": 0,
			"column": 2
		}
	},
	"RelationList": {
		"frame_args": {
			"manager": "grid",
			"row": 0,
			"column": 0,
			"sticky": "NWSE",
			"padx": [0, 10]
		}
	},
	"RelationTypes": {
		"frame_args": {
			"manager": "grid",
			"row": 1,
			"column": 0,
			"sticky": "NWSE",
			"padx": [0, 10]
		}
	},
	"RelationFrame1": {
		"frame_args": {
			"manager": "grid",
			"row": 1,
			"column": 1
		}
	},
	"RelationFrame2":{
		"frame_args": {
			"manager": "grid",
			"row": 1,
			"column": 2
		}
	}
}